[
    {
        "subject": "مادة الاقتصاد الجزئي",
        "videoId": "PLnKq9ZBuX35iWF4ifk8Kk-SvXWRZsJZjW"
    },
    {
        "subject": "مادة الرياضيات",
        "videoId": "PL_i4oGzXQNJqiHPRV7gAiIX2SbLVbxo9a"
    },
    {
        "subject": "فيديو واحد",
        "videoId": "xJXwrWEQhfw"
    },
    {
        "subject": "محاسبة مالية",
        "videoId": "PLlVh8HyJdQoW_ZAVlvFavIRWr8LbKDJrZ"
    },
    {
        "subject": "الاقتصاد الجزئي",
        "videoId": "PLnKq9ZBuX35iWF4ifk8Kk-SvXWRZsJZjW"
    },
    {
        "subject": "الرياضة البحته",
        "videoId": "PL_i4oGzXQNJqiHPRV7gAiIX2SbLVbxo9a"
    },
    {
        "subject": "مبادئ محاسبة",
        "videoId": "PLDYfSqIW22dEmTXZpMwWgcU0CHgpQRyzF"
    },
    {
        "subject": "اقتصاد جزئي",
        "videoId": "PLZNgmAibHc87UCn2Xvr0Kg-TKL8oiEkM6"
    }
]
